exception_handler/__init__.py
exception_handler/code_erros.py
exception_handler/config.py
exception_handler/factory_logging.py
exception_handler-1.0.2.dist-info/LICENSE.rst
exception_handler-1.0.2.dist-info/METADATA
exception_handler-1.0.2.dist-info/WHEEL
exception_handler-1.0.2.dist-info/top_level.txt
exception_handler-1.0.2.dist-info/RECORD
