Metadata-Version: 2.1
Name: exception-handler
Version: 1.0.2
Summary: Exception Handler
Home-page: https://github.com/PartyouPay/exception-handler.git
Author: Bruno Henrique de Paula
Author-email: bruno.henriquy@gmail.com
License: MIT
Platform: UNKNOWN
Classifier: Programming Language :: Python :: 3
Classifier: License :: OSI Approved :: MIT License
Classifier: Operating System :: OS Independent
Requires-Python: >=3.6
Requires-Dist: dynaconf
Requires-Dist: loguru
